acdpnet/__init__.py
acdpnet/__main__.py
acdpnet/filenode.py
acdpnet/nodes.py
acdpnet/server.py
acdpnet/services.py
acdpnet/tools.py
acdpnet/extension/__init__.py
acdpnet/extension/automatic.py
acdpnet/extension/transfer.py
acdpnet-2.2.1.dist-info/LICENSE
acdpnet-2.2.1.dist-info/METADATA
acdpnet-2.2.1.dist-info/WHEEL
acdpnet-2.2.1.dist-info/top_level.txt
acdpnet-2.2.1.dist-info/RECORD
