Metadata-Version: 2.1
Name: acdpnet
Version: 2.2.1
Summary: A TCP Services Frame
Home-page: https://github.com/A03HCY/Network-Core
Author: Aiden Hopkins
Author-email: acdphc@qq.com
License: UNKNOWN
Platform: UNKNOWN
Classifier: Programming Language :: Python :: 3
Classifier: License :: OSI Approved :: MIT License
Classifier: Operating System :: OS Independent
License-File: LICENSE
